{
	"configurations" : 
	[
		{
			"directories" : 
			[
				{
					"build" : ".",
					"jsonFile" : "directory-.-Debug-f5ebdc15457944623624.json",
					"minimumCMakeVersion" : 
					{
						"string" : "3.26"
					},
					"projectIndex" : 0,
					"source" : ".",
					"targetIndexes" : 
					[
						0
					]
				}
			],
			"name" : "Debug",
			"projects" : 
			[
				{
					"directoryIndexes" : 
					[
						0
					],
					"name" : "es_3",
					"targetIndexes" : 
					[
						0
					]
				}
			],
			"targets" : 
			[
				{
					"directoryIndex" : 0,
					"id" : "es_3::@6890427a1f51a3e7e1df",
					"jsonFile" : "target-es_3-Debug-f76362daaf37051fcbba.json",
					"name" : "es_3",
					"projectIndex" : 0
				}
			]
		}
	],
	"kind" : "codemodel",
	"paths" : 
	{
		"build" : "/home/nonnt66/Scaricati/uni/so/es_salvi/es_da_fare/es_3/cmake-build-debug",
		"source" : "/home/nonnt66/Scaricati/uni/so/es_salvi/es_da_fare/es_3"
	},
	"version" : 
	{
		"major" : 2,
		"minor" : 5
	}
}
